secrets_fields/apps.py
secrets_fields/backends/backends.py
secrets_fields/backends/encrypted.py
secrets_fields/backends/secretsmanager.py
secrets_fields/checks.py
secrets_fields/exceptions.py
secrets_fields/fields.py
secrets_fields/management/__init__.py
secrets_fields/management/commands/__init__.py
secrets_fields/management/commands/generate_fernet_key.py
secrets_fields/management/commands/migrate_encrypted.py
secrets_fields/settings.py
secrets_fields/types.py
secrets_fields/util.py
secrets_fields/widgets.py
django_secrets_fields-1.0.5.dist-info/LICENSE
django_secrets_fields-1.0.5.dist-info/METADATA
django_secrets_fields-1.0.5.dist-info/WHEEL
django_secrets_fields-1.0.5.dist-info/RECORD
